StarStruct-0.9.1.dist-info/DESCRIPTION.rst
StarStruct-0.9.1.dist-info/METADATA
StarStruct-0.9.1.dist-info/RECORD
StarStruct-0.9.1.dist-info/WHEEL
StarStruct-0.9.1.dist-info/entry_points.txt
StarStruct-0.9.1.dist-info/metadata.json
StarStruct-0.9.1.dist-info/top_level.txt
starstruct/__init__.py
starstruct/element.py
starstruct/elementbase.py
starstruct/elementdiscriminated.py
starstruct/elementenum.py
starstruct/elementfixedpoint.py
starstruct/elementlength.py
starstruct/elementnum.py
starstruct/elementpad.py
starstruct/elementstring.py
starstruct/elementvariable.py
starstruct/message.py
starstruct/modes.py
starstruct/tests/__init__.py
starstruct/tests/conftest.py
starstruct/tests/test_elementbase.py
starstruct/tests/test_elementenum.py
starstruct/tests/test_elementfixedpoint.py
starstruct/tests/test_elementlength.py
starstruct/tests/test_elementnum.py
starstruct/tests/test_elementpad.py
starstruct/tests/test_elementstring.py
starstruct/tests/test_elementvariable.py
starstruct/tests/test_length.py
starstruct/tests/test_message.py
