Metadata-Version: 2.0
Name: StarStruct
Version: 0.9.1
Summary: StarStruct allows for easy binary stream pack/unpack
Home-page: https://github.com/sprout42/StarStruct
Author: Aaron Cornelius
Author-email: a.aaron.cornelius@gmail.com
License: MIT
Platform: UNKNOWN
Classifier: Development Status :: 4 - Beta
Classifier: Natural Language :: English
Classifier: Operating System :: OS Independent
Classifier: Programming Language :: Python
Classifier: Programming Language :: Python :: 3.5
